netboot-config
setup.py
netboot_config/__init__.py
netboot_config/config.py
netboot_config/model.py
netboot_config/network.py
netboot_config.egg-info/PKG-INFO
netboot_config.egg-info/SOURCES.txt
netboot_config.egg-info/dependency_links.txt
netboot_config.egg-info/top_level.txt
test/test_config.py
test/test_model.py
test/test_network.py