Metadata-Version: 2.1
Name: netboot-config
Version: 0.1.29
Summary: Generator for KIWI based netboot config files
Home-page: UNKNOWN
Author: Andreas Würl
Author-email: andreas.wuerl@uniscon.com
License: UNKNOWN
Platform: UNKNOWN
Classifier: Development Status :: 3 - Alpha
Classifier: Intended Audience :: Developers
Classifier: Topic :: Software Development :: Build Tools
Classifier: Programming Language :: Python :: 3.5
Classifier: License :: OSI Approved :: Apache Software License
Classifier: Operating System :: POSIX :: Linux
